PyKCS11/LowLevel.py
PyKCS11/_LowLevel.cp312-win_amd64.pyd
PyKCS11/__init__.py
PyKCS11/constants.py
pykcs11-1.5.18.dist-info/licenses/COPYING
pykcs11-1.5.18.dist-info/METADATA
pykcs11-1.5.18.dist-info/WHEEL
pykcs11-1.5.18.dist-info/top_level.txt
pykcs11-1.5.18.dist-info/RECORD
