Metadata-Version: 2.1
Name: PyKCS11
Version: 1.5.18
Summary: A Full PKCS#11 wrapper for Python
Home-page: https://github.com/LudovicRousseau/PyKCS11
Download-URL: http://sourceforge.net/projects/pkcs11wrap/files/pykcs11/
Author: Giuseppe Amato (Midori)
Author-email: paipai@tiscali.it
Maintainer: Ludovic Rousseau
Maintainer-email: ludovic.rousseau@free.fr
License: GPL
Keywords: crypto,pki,pkcs11,c++
Platform: Win32 Unix
Classifier: Development Status :: 5 - Production/Stable
Classifier: Intended Audience :: Developers
Classifier: License :: OSI Approved :: GNU General Public License (GPL)
Classifier: Natural Language :: English
Classifier: Operating System :: Microsoft :: Windows
Classifier: Operating System :: OS Independent
Classifier: Operating System :: Unix
Classifier: Programming Language :: C
Classifier: Programming Language :: C++
Classifier: Programming Language :: Python
Classifier: Topic :: Security :: Cryptography
Classifier: Topic :: Software Development :: Libraries :: Python Modules
License-File: COPYING
